{
    "@context": {
        "@vocab": "https://schema.org/",
        "geosparql": "http://www.opengis.net/ont/geosparql#"
    },
    "@id": "http://geonetwork.iode.org/id/76d66a0e-7c78-40a0-bac4-9e2a04ce385a",
    "@type": "Dataset",
    "geosparql:hasGeometry": {
        "@type": "http://www.opengis.net/ont/sf#Polygon",
        "geosparql:asWKT": {
            "@type": "geosparql:wktLiteral",
            "@value": "POLYGON((15 -35, 15 -25, 45 -25, 45 -35, 15 -35))"
        },
        "geosparql:crs": {
            "@id": "http://www.opengis.net/def/crs/OGC/1.3/CRS84"
        }
    },
    "description": "This data is from the Environmental office of Durban",
    "keywords": "Land Surface, Coast, KwaZulu Natal,South Africa, Land Surface, Coast, KwaZulu Natal,South Africa, Land Surface, Coast, KwaZulu Natal,South Africa, South Africa",
    "name": "South Africa: KwaZulu-Natal Coastal Types"
}