{
    "@context": {
        "@vocab": "https://schema.org/",
        "geosparql": "http://www.opengis.net/ont/geosparql#"
    },
    "@id": "http://maspawio.net/layers/geonode%3Awio_100km_offcoastline_buffer_1",
    "@type": "Dataset",
    "geosparql:hasGeometry": {
        "@type": "http://www.opengis.net/ont/sf#Polygon",
        "geosparql:asWKT": {
            "@type": "geosparql:wktLiteral",
            "@value": "POLYGON((29.0239869070701 -31.8342936409387, 29.0239869070701 11.9809999470899, 63.5020828253622 11.9809999470899, 63.5020828253622 -31.8342936409387, 29.0239869070701 -31.8342936409387))"
        },
        "geosparql:crs": {
            "@id": "http://www.opengis.net/def/crs/OGC/1.3/CRS84"
        }
    },
    "description": "This coverage is a vector polygon/layer illustrating a coastal buffer that extends a 100 km on land. The layer was produced by CORDIO based on a high resolution coastal line derived from the GSHHS_shp: Shape-files (polygons) shorelines.",
    "keywords": "coastal, buffer, Africa, Western Indian Ocean, Comoros, Kenya, Madagascar, Mauritius, Mayotte, Mozambique, Reunion, Seychelles, Somalia, South Africa, Tanzania",
    "name": "WIO 100 km coastal buffer",
    "url": "http://maspawio.net/layers/geonode%3Awio_100km_offcoastline_buffer_1"
}