{
    "@context": {
        "@vocab": "https://schema.org/",
        "geosparql": "http://www.opengis.net/ont/geosparql#"
    },
    "@id": "http://maspawio.net/id/ec0e071c-cf56-11e7-896f-0a735f7a740c",
    "@type": "Dataset",
    "geosparql:hasGeometry": {
        "@type": "http://www.opengis.net/ont/sf#Polygon",
        "geosparql:asWKT": {
            "@type": "geosparql:wktLiteral",
            "@value": "POLYGON((42.54773333 11.50426667, 42.54773333 12.22221667, 43.42325 12.22221667, 43.42325 11.50426667, 42.54773333 11.50426667))"
        },
        "geosparql:crs": {
            "@id": "http://www.opengis.net/def/crs/OGC/1.3/CRS84"
        }
    },
    "description": "This spatial coverage includes vector points and point labels that describe CORDIO and PRAREV in-water survey sites of the broader Djibouti Seascape. Each site has a set of fish and benthic community variables distinguishing it from the surrounding sites. These characteristics include site name, functional group, mean fish biomass (kg/ha) and mean fish abundance (individuals/ha).",
    "keywords": "Djibouti, omnivores biomass, piscivores biomass, Africa, East Africa, Djibouti",
    "name": "Djibouti 2014 and 2016 Mean Piscivores  & Omnivores Biomass kg_ha"
}