{
    "@context": {
        "@vocab": "https://schema.org/",
        "geosparql": "http://www.opengis.net/ont/geosparql#"
    },
    "@id": "https://emodnet.ec.europa.eu/geonetwork/srv/eng/catalog.search#/metadata/fc26d4d11840398857e1d4961ef8fa7c3436ea36",
    "@type": "Dataset",
    "geosparql:hasGeometry": {
        "@type": "http://www.opengis.net/ont/sf#Polygon",
        "geosparql:asWKT": {
            "@type": "geosparql:wktLiteral",
            "@value": "POLYGON((4.228 51.117, 4.228 51.36, 4.405 51.36, 4.405 51.117, 4.228 51.117))"
        },
        "geosparql:crs": {
            "@id": "http://www.opengis.net/def/crs/OGC/1.3/CRS84"
        }
    },
    "keywords": [
        "Beneden-Zeeschelde",
        "bathymetrie",
        "diepte",
        "morfodynamiek",
        "vaargeul",
        "Schelde"
    ],
    "name": "Bathymetrie Beneden-Zeeschelde, dieptecontouren (MDK)",
    "url": "https://emodnet.ec.europa.eu/geonetwork/srv/eng/catalog.search#/metadata/fc26d4d11840398857e1d4961ef8fa7c3436ea36"
}