{
    "@context": {
        "@vocab": "https://schema.org/",
        "geosparql": "http://www.opengis.net/ont/geosparql#"
    },
    "@id": "https://emodnet.ec.europa.eu/geonetwork/srv/eng/catalog.search#/metadata/0c026e9147e73d2b460255536e5e98eceb48d775",
    "@type": "Dataset",
    "geosparql:hasGeometry": {
        "@type": "http://www.opengis.net/ont/sf#Polygon",
        "geosparql:asWKT": {
            "@type": "geosparql:wktLiteral",
            "@value": "POLYGON((4.215493119090693 51.1230977397952, 4.215493119090693 51.37468318850425, 4.402168248028673 51.37468318850425, 4.402168248028673 51.1230977397952, 4.215493119090693 51.1230977397952))"
        },
        "geosparql:crs": {
            "@id": "http://www.opengis.net/def/crs/OGC/1.3/CRS84"
        }
    },
    "description": "An ecotope map of the Lower Sea Scheldt for 2015 was created based on two fundamental information layers: a physiotopic map and a geomorphological map. Ecotope maps are used to follow up the evolution of the diversity of habitats.",
    "keywords": [
        "ecotopenkaart",
        "fysiotopenkaart",
        "geomorfologische kaart",
        "Zeeschelde",
        "abiotische eenheden",
        "raster",
        "hard",
        "zacht",
        "substraat",
        "klei",
        "getijde",
        "schor",
        "dijk",
        "vegetatie",
        "slik",
        "schorren",
        "slikken",
        "Ecotope map",
        "physiotopic map",
        "geomorphological map",
        "Sea Scheldt",
        "abiotic units",
        "grid",
        "hard",
        "soft",
        "substrate",
        "clay",
        "tide",
        "marsh",
        "dyke",
        "vegetation",
        "mud",
        "salt marshes",
        "mud flats",
        "Habitats and biotopes"
    ],
    "name": "Ecotope map (Lower Sea Scheldt, 2015)",
    "url": "https://emodnet.ec.europa.eu/geonetwork/srv/eng/catalog.search#/metadata/0c026e9147e73d2b460255536e5e98eceb48d775"
}