{
    "@context": {
        "@vocab": "https://schema.org/"
    },
    "@id": "https://raw.githubusercontent.com/iodepo/odis-arch/master/collection/tempHosting/data-maspawio/maspawio-935425aa-78f5-11e7-9661-0a735f7a740c.json",
    "@type": "Dataset",
    "description": "Mozambique Channel Sediment thickness is derived  from the digital total-sediment-thickness database for the world's oceans. The data  illustrates areas with low, minimum and high sediment deposition/thickness.",
    "keywords": [
        "sediments",
        "thickness",
        "Africa",
        "East Africa",
        "Comoros",
        "Madagascar",
        "Mayotte",
        "Mozambique",
        "United Republic of Tanzania"
    ],
    "name": "Mozambique Channel Sediment thickness",
    "spatialCoverage": {
        "@type": "Place",
        "geo": {
            "@type": "GeoShape",
            "box": "-29.132088365679813 34.201994133459074 -9.336829437261658 50.7534921450356"
        }
    },
    "url": "http://maspawio.net/layers/geonode%3Amozambique_channel_sediment_thickness"
}