{
    "@context": {
        "@vocab": "https://schema.org/",
        "geosparql": "http://www.opengis.net/ont/geosparql#"
    },
    "@id": "https://raw.githubusercontent.com/iodepo/odis-arch/schema-dev-jm/code/notebooks/Exploration/data-ama/ama-bec3503b-03c7-4057-b78b-59e65fe632c7.json",
    "@type": "Dataset",
    "geosparql:hasGeometry": {
        "@type": "http://www.opengis.net/ont/sf#Polygon",
        "geosparql:asWKT": {
            "@type": "geosparql:wktLiteral",
            "@value": "POLYGON((10 -40, 10 -4, 50 -4, 50 -40, 10 -40))"
        },
        "geosparql:crs": {
            "@id": "http://www.opengis.net/def/crs/OGC/1.3/CRS84"
        }
    },
    "description": "GADM is a spatial database of the location of the world's administrative areas (or adminstrative boundaries) for use in GIS and similar software. Administrative areas in this database are countries and lower level subdivisions such as provinces, departments, bibhag, bundeslander, daerah istimewa, fivondronana, krong, landsvæðun, opština, sous-préfectures, counties, and thana. GADM describes where these administrative areas are (the \"spatial features\"), and for each area it provides some attributes, foremost being the name and variant names.",
    "keywords": [
        "HUMAN DIMENSIONS",
        "BOUNDARIES",
        "ADMINISTRATIVE DIVISIONS",
        "HUMAN DIMENSIONS",
        "BOUNDARIES",
        "POLITICAL DIVISIONS",
        "South Africa",
        "Atlas"
    ],
    "name": "South Africa Extended AOI: Administrative Areas from GADM",
    "url": "http://www.gadm.org/country"
}