{
    "@context": {
        "@vocab": "https://schema.org/",
        "geosparql": "http://www.opengis.net/ont/geosparql#"
    },
    "@id": "http://maspawio.net/id/15",
    "@type": "Dataset",
    "geosparql:hasGeometry": {
        "@type": "http://www.opengis.net/ont/sf#Polygon",
        "geosparql:asWKT": {
            "@type": "geosparql:wktLiteral",
            "@value": "POLYGON(11.6835277504  51.2585487505  11.6835277504  30.0734768868 -31.2227794124  30.0734768868  -31.2227794124  51.2585487505 11.6835277504 51.2585487505)"
        },
        "geosparql:crs": {
            "@id": "http://www.opengis.net/def/crs/OGC/1.3/CRS84"
        }
    },
    "description": "WIO  high resolution coastline vector layer (line) show s the approximate  boundary between land and sea. The layer was derived by CORDIO EA  from the GSHHS shorelines dataset used by GMT, the Generic Mapping Tools.",
    "keywords": "coast line",
    "name": "WIO high resolution coast line"
}