{
    "@context": {
        "@vocab": "https://schema.org/",
        "geosparql": "http://www.opengis.net/ont/geosparql#"
    },
    "@id": "https://geodata.benguelacc.org/id/1df23c2a-6266-11ec-8d97-0242ac1c0006",
    "@type": "Dataset",
    "geosparql:hasGeometry": {
        "@type": "http://www.opengis.net/ont/sf#Polygon",
        "geosparql:asWKT": {
            "@type": "geosparql:wktLiteral",
            "@value": "POLYGON((11.3853330612183 -25.0000267028809, 11.3853330612183 -17.2429466247559, 14.839168548584 -17.2429466247559, 14.839168548584 -25.0000267028809, 11.3853330612183 -25.0000267028809))"
        },
        "geosparql:crs": {
            "@id": "http://www.opengis.net/def/crs/OGC/1.3/CRS84"
        }
    },
    "description": "Generalised spawning areas of pelagic fish - sardine, horse mackerel, anchovy.",
    "keywords": "Current Status Report, Spawning, Namibia",
    "name": "NAM CSR Spawning areas of pelagic fish"
}