{
    "@context": {
        "@vocab": "https://schema.org/",
        "geosparql": "http://www.opengis.net/ont/geosparql#"
    },
    "@id": "https://geo.vliz.be/geoserver/Kustportaal/ows?service=WMS&request=GetLegendGraphic&format=image%2Fpng&width=20&height=20&layer=baggerlocaties_2012",
    "@type": "Dataset",
    "geosparql:hasGeometry": {
        "@type": "http://www.opengis.net/ont/sf#Polygon",
        "geosparql:asWKT": {
            "@type": "geosparql:wktLiteral",
            "@value": "POLYGON((2.71892118961298 51.1444419053599, 2.71892118961298 51.4588233247343, 3.93201768015395 51.4588233247343, 3.93201768015395 51.1444419053599, 2.71892118961298 51.1444419053599))"
        },
        "geosparql:crs": {
            "@id": "http://www.opengis.net/def/crs/OGC/1.3/CRS84"
        }
    },
    "description": "The location of dredging and dumping sites in the BNS for the year 2012.",
    "keywords": "baggeren, baggerlocaties, stortlocaties, Area management / restriction / regulation zones & reporting units",
    "name": "Dredging and dumping sites (Belgian part of North Sea, 2012)",
    "url": "https://geo.vliz.be/geoserver/Kustportaal/ows?service=WMS&request=GetLegendGraphic&format=image%2Fpng&width=20&height=20&layer=baggerlocaties_2012"
}