{
    "@context": {
        "@vocab": "https://schema.org/",
        "geosparql": "http://www.opengis.net/ont/geosparql#"
    },
    "@id": "https://geo.vliz.be/geoserver/MarineRegions/ows?service=WMS&request=GetLegendGraphic&format=image%2Fpng&width=20&height=20&layer=iho_quadrants_20150810",
    "@type": "Dataset",
    "geosparql:hasGeometry": {
        "@type": "http://www.opengis.net/ont/sf#Polygon",
        "geosparql:asWKT": {
            "@type": "geosparql:wktLiteral",
            "@value": "POLYGON((-181.800003051758 -86.3476409912109, -181.800003051758 90.8773574829102, 181.800018310547 90.8773574829102, 181.800018310547 -86.3476409912109, -181.800003051758 -86.3476409912109))"
        },
        "geosparql:crs": {
            "@id": "http://www.opengis.net/def/crs/OGC/1.3/CRS84"
        }
    },
    "keywords": "",
    "name": "IHO quadrants (20150810)",
    "url": "https://geo.vliz.be/geoserver/MarineRegions/ows?service=WMS&request=GetLegendGraphic&format=image%2Fpng&width=20&height=20&layer=iho_quadrants_20150810"
}