{
    "@context": {
        "@vocab": "https://schema.org/",
        "geosparql": "http://www.opengis.net/ont/geosparql#"
    },
    "@id": "https://geo.vliz.be/geoserver/Scheldemonitor/ows?service=WMS&request=GetLegendGraphic&format=image%2Fpng&width=20&height=20&layer=mt_contour_20100115",
    "@type": "Dataset",
    "geosparql:hasGeometry": {
        "@type": "http://www.opengis.net/ont/sf#Polygon",
        "geosparql:asWKT": {
            "@type": "geosparql:wktLiteral",
            "@value": "POLYGON((2.531 50.977, 2.531 51.629, 4.771 51.629, 4.771 50.977, 2.531 50.977))"
        },
        "geosparql:crs": {
            "@id": "http://www.opengis.net/def/crs/OGC/1.3/CRS84"
        }
    },
    "keywords": "Scheldemonitor",
    "name": "Contour lines of the Scheldt Estuary",
    "url": "https://geo.vliz.be/geoserver/Scheldemonitor/ows?service=WMS&request=GetLegendGraphic&format=image%2Fpng&width=20&height=20&layer=mt_contour_20100115"
}