{
    "@context": {
        "@vocab": "https://schema.org/"
    },
    "@id": "https://raw.githubusercontent.com/iodepo/odis-arch/master/collection/tempHosting/data-caribbeanmarineatlas/caribbeanmarineatlas-e6d24f90-e366-11ed-b5a4-0242ac120007.json",
    "@type": "Dataset",
    "description": "<p>The data in the EMODnet Grid should not be used for navigation or any purpose relating to safety at sea.</p>",
    "keywords": [
        "GeoTIFF",
        "HillshadeBatimetria2022",
        "WCS",
        "Global"
    ],
    "name": "HillshadeBatimetria2022",
    "spatialCoverage": {
        "@type": "Place",
        "geo": {
            "@type": "GeoShape",
            "box": "10.99999999964611 -70.5 18.999999999418527 -59.5"
        }
    },
    "url": "https://www.caribbeanmarineatlas.net/layers/HillshadeBatimetria2022:geonode:HillshadeBatimetria2022"
}