{
    "@context": {
        "@vocab": "https://schema.org/"
    },
    "@id": "https://raw.githubusercontent.com/iodepo/odis-arch/master/collection/tempHosting/data-caribbeanmarineatlas/caribbeanmarineatlas-b21a0998-bd0e-475f-bb7d-e0824b5386bf.json",
    "@type": "Dataset",
    "description": "Sea Surface Height (Annual Mean)",
    "keywords": [
        "ArcGIS REST MapServer",
        "ESRI",
        "Sea Surface Height (Annual Mean)",
        "Global",
        "Africa",
        "Central Africa",
        "West Africa",
        "Pacific",
        "Kiribati"
    ],
    "name": "Sea Surface Height (Annual Mean)",
    "spatialCoverage": {
        "@type": "Place",
        "geo": {
            "@type": "GeoShape",
            "box": "-17.555000021654322 -179.99998856633965 74.68531345559185 179.99998856633965"
        }
    },
    "url": "https://www.caribbeanmarineatlas.net/layers/httpscoastnoaagovarcgisrestservicesoceanreportingtoolseasurfaceheight_annualmeanmapserver:0-sea-surface-height-annual-mean"
}