{
    "@context": {
        "@vocab": "https://schema.org/"
    },
    "@id": "https://raw.githubusercontent.com/iodepo/odis-arch/master/collection/tempHosting/data-caribbeanmarineatlas/caribbeanmarineatlas-5c745016-0671-11eb-b08b-0242ac120008.json",
    "@type": "Dataset",
    "description": "The seagrass of Trinidad and Tobago",
    "keywords": [
        "features",
        "seagrass",
        "tm_trinidad_and_tobago_seagrass_2007_1000",
        "Trinidad and Tobago",
        "Global"
    ],
    "name": "TM_TTO_seagrass_2007_1000",
    "spatialCoverage": {
        "@type": "Place",
        "geo": {
            "@type": "GeoShape",
            "box": "10,3269548416138 -61,6061820983887 11,1800518035889 -60,8167419433594"
        }
    },
    "url": "https://www.caribbeanmarineatlas.net/layers/cma_geonode_data:geonode:tm_trinidad_and_tobago_seagrass_2007_1000"
}